LICENCE.txt
MANIFEST.in
README.md
README.rst
setup.cfg
setup.py
pyforchange/__init__.py
pyforchange/cell.py
pyforchange/covidplot.py
pyforchange.egg-info/PKG-INFO
pyforchange.egg-info/SOURCES.txt
pyforchange.egg-info/dependency_links.txt
pyforchange.egg-info/top_level.txt