Metadata-Version: 2.1
Name: pyforchange
Version: 2.0.2
Summary: pythonforchange.github.io
Home-page: https://github.com/PythonForChange/pyforchange
Author: Python For Change
Author-email: pythonforchange@gmail.com
License: MIT
Download-URL: https://github.com/PythonForChange/pyforchange/archive/refs/tags/v2.0.2.tar.gz
Keywords: covid,logging,language,plot,life
Platform: UNKNOWN
Classifier: Programming Language :: Python :: 3
